{
  "questions": [
    {
      "type": "MCQ",
      "source": "https://www.freetimelearning.com/online-quiz/node-js-quiz.php?page=1",
      "statement": "Node.js is \\_\\_\\_\\_\\_\\_\\_\\_\\_\\_\\_ Language.",
      "options": [
        { "text": "Server Side", "correct": true },
        { "text": "Client Side", "correct": false },
        { "text": "Both", "correct": false },
        { "text": "None of the above", "correct": false }
      ]
    },
    {
      "type": "MCQ",
      "source": "https://www.freetimelearning.com/online-quiz/node-js-quiz.php?page=1",
      "statement": "Which of the followings are valid languages for Node.js?",
      "options": [
        { "text": "C#", "correct": false },
        { "text": "C++", "correct": false },
        { "text": "Javascript", "correct": true },
        { "text": "Java", "correct": false }
      ]
    },
    {
      "type": "MCQ",
      "source": "https://www.freetimelearning.com/online-quiz/node-js-quiz.php?page=1",
      "statement": "Which extension is used to save NodeJs files?",
      "options": [
        { "text": ".node", "correct": false },
        { "text": ".js", "correct": true },
        { "text": ".txt", "correct": false },
        { "text": ".java", "correct": false }
      ]
    },
    {
      "type": "MCQ",
      "source": "https://www.freetimelearning.com/online-quiz/node-js-quiz.php?page=1",
      "statement": "In Node process is \\_\\_\\_\\_\\_\\_",
      "options": [
        { "text": "Global Object", "correct": true },
        { "text": "Local Object", "correct": false },
        { "text": "Both", "correct": false },
        { "text": "None of the Above", "correct": false }
      ]
    },
    {
      "type": "MCQ",
      "source": "https://www.freetimelearning.com/online-quiz/node-js-quiz.php?page=1",
      "statement": "Which function is used to include modules in Node Js.",
      "options": [
        { "text": "include();", "correct": false },
        { "text": "attach();", "correct": false },
        { "text": "require();", "correct": true },
        { "text": "All of the above", "correct": false }
      ]
    },
    {
      "type": "MCQ",
      "source": "https://www.freetimelearning.com/online-quiz/node-js-quiz.php?page=1",
      "statement": "Which of following is not builtin node module.",
      "options": [
        { "text": "zlib", "correct": false },
        { "text": "https", "correct": false },
        { "text": "dgram", "correct": false },
        { "text": "fsread", "correct": true }
      ]
    },
    {
      "type": "MCQ",
      "source": "https://www.freetimelearning.com/online-quiz/node-js-quiz.php?page=1",
      "statement": "How Node.js modules are availble externally",
      "options": [
        { "text": "module.exports", "correct": true },
        { "text": "module.expose", "correct": false },
        { "text": "module.spread", "correct": false },
        { "text": "None of the Above", "correct": false }
      ]
    },
    {
      "type": "MCQ",
      "source": "https://www.freetimelearning.com/online-quiz/node-js-quiz.php?page=1",
      "statement": "What does the fs module stand for?",
      "options": [
        { "text": "File Service", "correct": false },
        { "text": "File System", "correct": true },
        { "text": "File Store", "correct": false },
        { "text": "None of the above", "correct": false }
      ]
    },
    {
      "type": "MCQ",
      "source": "https://www.freetimelearning.com/online-quiz/node-js-quiz.php?page=1",
      "statement": "What is the default scope in Node.js application.",
      "options": [
        { "text": "Local", "correct": true },
        { "text": "Public", "correct": false },
        { "text": "Private", "correct": false },
        { "text": "Global", "correct": false }
      ]
    },
    {
      "type": "MCQ",
      "source": "https://www.freetimelearning.com/online-quiz/node-js-quiz.php?page=1",
      "statement": "Which of the following is true about RESTful web services?",
      "options": [
        {
          "text": "Webservices based on REST Architecture are known as RESTful web services",
          "correct": false
        },
        {
          "text": "Webservices uses HTTP methods to implement the concept of REST architecture",
          "correct": false
        },
        { "text": "Both of the above", "correct": true },
        { "text": "None of the above", "correct": false }
      ]
    },
    {
      "type": "MCQ",
      "source": "https://www.freetimelearning.com/online-quiz/node-js-quiz.php?page=2",
      "statement": "In Nodejs how node based web servers differ from traditional web servers?",
      "options": [
        {
          "text": "Node based server uses a single threaded model and can serve much larger number of requests compared to any traditional server like Apache HTTP Server.",
          "correct": true
        },
        {
          "text": "Node based server process request much faster than traditional server.",
          "correct": false
        },
        {
          "text": "There is no much difference between the two.",
          "correct": false
        },
        { "text": "All of the above", "correct": false }
      ]
    },
    {
      "type": "MCQ",
      "source": "https://www.freetimelearning.com/online-quiz/node-js-quiz.php?page=2",
      "statement": "What are the key features of Node.js?",
      "options": [
        {
          "text": "Builds fast and scalable network Applications",
          "correct": false
        },
        {
          "text": "Highly scalable servers for Web Applications",
          "correct": false
        },
        { "text": "Real time Data intensive", "correct": false },
        { "text": "All of the above", "correct": true }
      ]
    },
    {
      "type": "MCQ",
      "source": "https://www.freetimelearning.com/online-quiz/node-js-quiz.php?page=2",
      "statement": "How can we check the current version of NPM?",
      "options": [
        { "text": "npm --version", "correct": true },
        { "text": "npm --ver", "correct": false },
        { "text": "npm help", "correct": false },
        { "text": "None of the above", "correct": false }
      ]
    },
    {
      "type": "MCQ",
      "source": "https://www.freetimelearning.com/online-quiz/node-js-quiz.php?page=2",
      "statement": "What is the advantage of using node.js?",
      "options": [
        {
          "text": "It provides an easy way to build scalable network programs",
          "correct": false
        },
        { "text": "Great concurrency", "correct": false },
        { "text": "Generally fast", "correct": false },
        { "text": "All of these", "correct": true }
      ]
    },
    {
      "type": "MCQ",
      "source": "https://www.freetimelearning.com/online-quiz/node-js-quiz.php?page=2",
      "statement": "Why a Node.JS code is pretty fast although being written in JavaScript?",
      "options": [
        {
          "text": "Node.JS internally converts JavaScript code to Java based code and then execute the same",
          "correct": false
        },
        {
          "text": "Node.JS internally converts JavaScript code to C based code and then execute the same",
          "correct": false
        },
        {
          "text": "Being built on Google Chrome's V8 JavaScript Engine",
          "correct": true
        },
        { "text": "None of the above", "correct": false }
      ]
    },
    {
      "type": "MCQ",
      "source": "https://www.freetimelearning.com/online-quiz/node-js-quiz.php?page=2",
      "statement": "What is REPL in Node.js?",
      "options": [
        { "text": "Eval", "correct": false },
        { "text": "Print", "correct": false },
        { "text": "Loop", "correct": false },
        { "text": "All of these", "correct": true }
      ]
    },
    {
      "type": "MCQ",
      "source": "https://www.freetimelearning.com/online-quiz/node-js-quiz.php?page=2",
      "statement": "Which module is used to serve static resources in Node.js?",
      "options": [
        { "text": "http", "correct": false },
        { "text": "node-static", "correct": true },
        { "text": "node-resource", "correct": false },
        { "text": "static", "correct": false }
      ]
    },
    {
      "type": "MCQ",
      "source": "https://www.freetimelearning.com/online-quiz/node-js-quiz.php?page=2",
      "statement": "Is console a global object?",
      "options": [
        { "text": "false", "correct": false },
        { "text": "true", "correct": false },
        { "text": "null", "correct": true },
        { "text": "none", "correct": false }
      ]
    },
    {
      "type": "MCQ",
      "source": "https://www.freetimelearning.com/online-quiz/node-js-quiz.php?page=2",
      "statement": "Which of following are a valid form of route path?",
      "options": [
        { "text": "regular expressions", "correct": false },
        { "text": "string patterns", "correct": false },
        { "text": "strings", "correct": false },
        { "text": "All of above", "correct": true }
      ]
    },
    {
      "type": "MCQ",
      "source": "https://www.freetimelearning.com/online-quiz/node-js-quiz.php?page=2",
      "statement": "Command to show installed version of Node?",
      "options": [
        { "text": "$ npm --version", "correct": false },
        { "text": "$ npm getVersion", "correct": false },
        { "text": "$ node --version", "correct": true },
        { "text": "$ node getVersion", "correct": false }
      ]
    },
    {
      "type": "MCQ",
      "source": "https://www.freetimelearning.com/online-quiz/node-js-quiz.php?page=3",
      "statement": "Which of the following are not Node.js web application frameworks for?",
      "options": [
        { "text": "Geddy", "correct": false },
        { "text": "Express.js", "correct": false },
        { "text": "Aurelia", "correct": true },
        { "text": "Locomotive", "correct": false }
      ]
    },
    {
      "type": "MCQ",
      "source": "https://www.freetimelearning.com/online-quiz/node-js-quiz.php?page=3",
      "statement": "Which of the following template engines can be used with Node.js?",
      "options": [
        { "text": "Jade", "correct": false },
        { "text": "Vash", "correct": false },
        { "text": "Handlebars", "correct": true },
        { "text": "All of the above", "correct": false }
      ]
    },
    {
      "type": "MCQ",
      "source": "https://www.freetimelearning.com/online-quiz/node-js-quiz.php?page=3",
      "statement": "Which method returns the current working directory of the process.",
      "options": [
        { "text": "cwd();", "correct": false },
        { "text": "pwd();", "correct": false },
        { "text": "process.cwd();", "correct": true },
        { "text": "None of the above", "correct": false }
      ]
    },
    {
      "type": "MCQ",
      "source": "https://www.freetimelearning.com/online-quiz/node-js-quiz.php?page=3",
      "statement": "In which of the following areas, Node.js is perfect to use?",
      "options": [
        { "text": "I/O bound Applications", "correct": false },
        { "text": "Data Streaming Applications", "correct": false },
        {
          "text": "Data Intensive Realtime Applications DIRT",
          "correct": false
        },
        { "text": "All of the above", "correct": true }
      ]
    },
    {
      "type": "MCQ",
      "source": "https://www.freetimelearning.com/online-quiz/node-js-quiz.php?page=3",
      "statement": "What should you do in your code to improve your application’s performance?",
      "options": [
        { "text": "Use gzip compression", "correct": true },
        { "text": "Do logging correctly", "correct": false },
        { "text": "Handle exceptions properly", "correct": false },
        { "text": "Don’t use synchronous functions", "correct": false }
      ]
    },
    {
      "type": "MCQ",
      "source": "https://www.freetimelearning.com/online-quiz/node-js-quiz.php?page=3",
      "statement": "To install Node.js express module",
      "options": [
        { "text": "$ npm install express", "correct": true },
        { "text": "$ node install express", "correct": false },
        { "text": "$ install express", "correct": false },
        { "text": "None of the above", "correct": false }
      ]
    },
    {
      "type": "MCQ",
      "source": "https://www.freetimelearning.com/online-quiz/node-js-quiz.php?page=3",
      "statement": "Which of the following tool automates various tasks of Node.js application?",
      "options": [
        { "text": "Express.js", "correct": false },
        { "text": "GruntJS", "correct": true },
        { "text": "NPM", "correct": false },
        { "text": "None of the above", "correct": false }
      ]
    },
    {
      "type": "MCQ",
      "source": "https://www.freetimelearning.com/online-quiz/node-js-quiz.php?page=3",
      "statement": "What is Callback?",
      "options": [
        {
          "text": "Callback is a technique in which a method call back the caller method.",
          "correct": false
        },
        {
          "text": "Callback is an asynchronous equivalent for a function.",
          "correct": false
        },
        { "text": "Both of the above.", "correct": true },
        { "text": "None of the above.", "correct": false }
      ]
    },
    {
      "type": "MCQ",
      "source": "https://www.freetimelearning.com/online-quiz/node-js-quiz.php?page=3",
      "statement": "How do you kill a process in Node.js?",
      "options": [
        { "text": "Ctrl + B", "correct": false },
        { "text": "Ctrl + K", "correct": false },
        { "text": "Ctrl + T", "correct": false },
        { "text": "Ctrl + C", "correct": true }
      ]
    },
    {
      "type": "MCQ",
      "source": "https://www.freetimelearning.com/online-quiz/node-js-quiz.php?page=3",
      "statement": "How many Node object methods are available?",
      "options": [
        { "text": "14", "correct": false },
        { "text": "16", "correct": false },
        { "text": "18", "correct": true },
        { "text": "20", "correct": false }
      ]
    },
    {
      "type": "MCQ",
      "source": "https://www.freetimelearning.com/online-quiz/node-js-quiz.php?page=4",
      "statement": "Node.js terminal (REPL) is used for \\_\\_\\_\\_\\_\\_\\_\\_\\_.",
      "options": [
        { "text": "the preview of node.js application.", "correct": false },
        { "text": "testing node.js/JavaScript expressions", "correct": true },
        {
          "text": "executing browser’s JavaScript expressions.",
          "correct": false
        },
        { "text": "None of the above", "correct": false }
      ]
    },
    {
      "type": "MCQ",
      "source": "https://www.freetimelearning.com/online-quiz/node-js-quiz.php?page=4",
      "statement": "In Node.js APIs of Node.JS are which of the following?",
      "options": [
        { "text": "Asynchronous", "correct": true },
        { "text": "Synchronous", "correct": false },
        { "text": "Both of the above", "correct": false },
        { "text": "None of the above", "correct": false }
      ]
    },
    {
      "type": "MCQ",
      "source": "https://www.freetimelearning.com/online-quiz/node-js-quiz.php?page=4",
      "statement": "Which of the following class is used to create and consume custom events in Node.js?",
      "options": [
        { "text": "Events", "correct": false },
        { "text": "NodeEvent", "correct": false },
        { "text": "EventEmitter", "correct": true },
        { "text": "None of the above", "correct": false }
      ]
    },
    {
      "type": "MCQ",
      "source": "https://www.freetimelearning.com/online-quiz/node-js-quiz.php?page=4",
      "statement": "How can we create instance of http module?",
      "options": [
        { "text": "var http = require(\"http\")", "correct": true },
        { "text": "var http = new require(\"http\")", "correct": false },
        { "text": "var http = new http()", "correct": false },
        { "text": "None of the above", "correct": false }
      ]
    },
    {
      "type": "MCQ",
      "source": "https://www.freetimelearning.com/online-quiz/node-js-quiz.php?page=4",
      "statement": "Node.js supports which of the following platform?",
      "options": [
        { "text": "Windows", "correct": false },
        { "text": "Macintosh", "correct": false },
        { "text": "Unix/Linux", "correct": false },
        { "text": "All of the above", "correct": true }
      ]
    },
    {
      "type": "MCQ",
      "source": "https://www.freetimelearning.com/online-quiz/node-js-quiz.php?page=4",
      "statement": "In Nodejs what is use of underscore variable in REPL session?",
      "options": [
        { "text": "to store the result", "correct": false },
        { "text": "to get the last command used", "correct": false },
        { "text": "to get the last result", "correct": true },
        { "text": "None of the above", "correct": false }
      ]
    },
    {
      "type": "MCQ",
      "source": "https://www.freetimelearning.com/online-quiz/node-js-quiz.php?page=4",
      "statement": "Which statement is valid in using a Node module fs in a Node based application?",
      "options": [
        { "text": "import fs", "correct": false },
        { "text": "package fs", "correct": false },
        { "text": "var fs = require(\"fs\")", "correct": false },
        { "text": "var fs = import(\"fs\")", "correct": true }
      ]
    },
    {
      "type": "MCQ",
      "source": "https://www.freetimelearning.com/online-quiz/node-js-quiz.php?page=4",
      "statement": "REPL stands for.",
      "options": [
        { "text": "Read Eval Print Loop", "correct": true },
        { "text": "Read Eval Point Loop", "correct": false },
        { "text": "Read Earn Point Learn", "correct": false },
        { "text": "Research Eval Program Learn", "correct": false }
      ]
    },
    {
      "type": "MCQ",
      "source": "https://www.freetimelearning.com/online-quiz/node-js-quiz.php?page=4",
      "statement": "Command to start Node REPL",
      "options": [
        { "text": "$ node start", "correct": false },
        { "text": "$ node repl", "correct": false },
        { "text": "$ node", "correct": true },
        { "text": "$ node console", "correct": false }
      ]
    },
    {
      "type": "MCQ",
      "source": "https://www.freetimelearning.com/online-quiz/node-js-quiz.php?page=4",
      "statement": "For What npm stands?",
      "options": [
        { "text": "Node Project Manager", "correct": false },
        { "text": "Node Package Manager", "correct": true },
        { "text": "New Package Manager", "correct": false },
        { "text": "New Project Manager", "correct": false }
      ]
    },
    {
      "type": "MCQ",
      "source": "https://www.freetimelearning.com/online-quiz/node-js-quiz.php?page=5",
      "statement": "Command to list all modules that are install globally?",
      "options": [
        { "text": "$ npm ls -g", "correct": true },
        { "text": "$ node ls -g", "correct": false },
        { "text": "$ npm ls", "correct": false },
        { "text": "$ node ls", "correct": false }
      ]
    },
    {
      "type": "MCQ",
      "source": "https://www.freetimelearning.com/online-quiz/node-js-quiz.php?page=5",
      "statement": "Which of the following module is required for path specific operations ?",
      "options": [
        { "text": "Os module", "correct": false },
        { "text": "Path module", "correct": true },
        { "text": "Fs module", "correct": false },
        { "text": "All of the above.", "correct": false }
      ]
    },
    {
      "type": "MCQ",
      "source": "https://www.freetimelearning.com/online-quiz/node-js-quiz.php?page=5",
      "statement": "Which of the following are Node.js streams types?",
      "options": [
        { "text": "Writable", "correct": false },
        { "text": "Duplex", "correct": false },
        { "text": "Readable", "correct": false },
        { "text": "All of the above", "correct": true }
      ]
    },
    {
      "type": "MCQ",
      "source": "https://www.freetimelearning.com/online-quiz/node-js-quiz.php?page=5",
      "statement": "How do you install Nodemon using Node.js?",
      "options": [
        { "text": "npm install -g nodemon", "correct": true },
        { "text": "node install -g nodemon", "correct": false },
        { "text": "Both", "correct": false },
        { "text": "None of the above", "correct": false }
      ]
    },
    {
      "type": "MCQ",
      "source": "https://www.freetimelearning.com/online-quiz/node-js-quiz.php?page=5",
      "statement": "Node uses \\_\\_\\_\\_\\_\\_\\_\\_\\_ engine in core.",
      "options": [
        { "text": "Node En", "correct": false },
        { "text": "SpiderMonkey", "correct": false },
        { "text": "Chorme V8", "correct": true },
        { "text": "Microsoft Chakra", "correct": false }
      ]
    },
    {
      "type": "MCQ",
      "source": "https://www.freetimelearning.com/online-quiz/node-js-quiz.php?page=5",
      "statement": "Something that happened in our application that we can respond too.",
      "options": [
        { "text": "events", "correct": true },
        { "text": "actions", "correct": false },
        { "text": "procedures", "correct": false },
        { "text": "callback", "correct": false }
      ]
    },
    {
      "type": "MCQ",
      "source": "https://www.freetimelearning.com/online-quiz/node-js-quiz.php?page=5",
      "statement": "How to test if two nodes are equal?",
      "options": [
        { "text": "\\==", "correct": false },
        { "text": "equal()", "correct": false },
        { "text": "isEqualNode()", "correct": true },
        { "text": "None of the above", "correct": false }
      ]
    },
    {
      "type": "MCQ",
      "source": "https://www.freetimelearning.com/online-quiz/node-js-quiz.php?page=5",
      "statement": "Select all valid rout parameter formats",
      "options": [
        { "text": "/books/!:from-:to", "correct": true },
        { "text": "/books/:from-:to", "correct": false },
        { "text": "/books/:bookId/Id/", "correct": false },
        { "text": "None of the above", "correct": false }
      ]
    },
    {
      "type": "MCQ",
      "source": "https://www.freetimelearning.com/online-quiz/node-js-quiz.php?page=5",
      "statement": "Which of the following is the correct way to get a normalized path?",
      "options": [
        {
          "text": "os.normalize('/test/test1//2slashes/1slash/tab/..')",
          "correct": false
        },
        {
          "text": "fs.normalize('/test/test1//2slashes/1slash/tab/..')",
          "correct": false
        },
        {
          "text": "path.normalize('/test/test1//2slashes/1slash/tab/..')",
          "correct": true
        },
        { "text": "None of the above", "correct": false }
      ]
    },
    {
      "type": "MCQ",
      "source": "https://www.freetimelearning.com/online-quiz/node-js-quiz.php?page=5",
      "statement": "Which of the following is true about readable stream?",
      "options": [
        {
          "text": "Readable stream is used for read operation",
          "correct": false
        },
        {
          "text": "Output of readable stream can be input to a writable stream",
          "correct": false
        },
        { "text": "Both of the above", "correct": true },
        { "text": "None of the above", "correct": false }
      ]
    },
    {
      "type": "MCQ",
      "source": "https://www.freetimelearning.com/online-quiz/node-js-quiz.php?page=6",
      "statement": "How many node types are there in total?",
      "options": [
        { "text": "11", "correct": false },
        { "text": "12", "correct": true },
        { "text": "13", "correct": false },
        { "text": "14", "correct": false }
      ]
    },
    {
      "type": "MCQ",
      "source": "https://www.freetimelearning.com/online-quiz/node-js-quiz.php?page=6",
      "statement": "What is the purpose of the Node object property ownerDocument?",
      "options": [
        { "text": "Returns the parent node", "correct": false },
        { "text": "Returns the immediate node", "correct": false },
        { "text": "Returns the last element", "correct": false },
        { "text": "Returns the root element", "correct": true }
      ]
    },
    {
      "type": "MCQ",
      "source": "https://www.freetimelearning.com/online-quiz/node-js-quiz.php?page=6",
      "statement": "Which method is used to compare the placement of two nodes in the DOM hierarchy (document)?",
      "options": [
        { "text": "cloneNode()", "correct": false },
        { "text": "compareDocumentPosition()", "correct": true },
        { "text": "getUserData()", "correct": false },
        { "text": "getFeature()", "correct": false }
      ]
    },
    {
      "type": "MCQ",
      "source": "https://www.freetimelearning.com/online-quiz/node-js-quiz.php?page=6",
      "statement": "Which of the following Node object property returns the node immediately before a node?",
      "options": [
        { "text": "previousSibling", "correct": true },
        { "text": "textContent", "correct": false },
        { "text": "localName", "correct": false },
        { "text": "index", "correct": false }
      ]
    }
  ]
}
